{
  "search_date": "2026-06-06T15:36:54.472530",
  "count": 8,
  "fresh_buildings": 4,
  "seen_buildings": 4,
  "listings": [
    {
      "mls_number": "27238147",
      "title": "Bâtisse commerciale à louer à Boucherville, Montérégie, 100, boulevard De Montarville, local 80, 27238147",
      "category": "Batisse Commerciale",
      "address": "Montérégie, 100, boulevard De Montarville, local 80",
      "city": "Montérégie",
      "price_value": "16.77",
      "price_display": "",
      "latitude": 45.60256489086896,
      "longitude": -73.45128242857754,
      "photo_count": 0,
      "listing_url": "https://www.centris.ca/fr/batisse-commerciale~a-louer~boucherville/27238147",
      "sqft": 680,
      "description": "Sur Centris.ca, découvrez la plus grande offre de propriété résidentielle à vendre.",
      "broker": "NAI TERRAMONT COMMERCIAL Agence immobilière commerciale",
      "area": "boucherville",
      "area_label": "Boucherville",
      "transaction_type": "lease",
      "first_seen": "2026-06-06",
      "building_seen_before": true
    },
    {
      "mls_number": "12212839",
      "title": "Local commercial à louer à Longueuil (Le Vieux-Longueuil), Montérégie, 1800 - 1860, boulevard Marie-Victorin, local 203/206, 12212839",
      "category": "Local Commercial",
      "address": "Montérégie, 1800 - 1860, boulevard Marie-Victorin, local 203/206",
      "city": "Montérégie",
      "price_value": "12.5",
      "price_display": "",
      "latitude": 45.56882101809606,
      "longitude": -73.48589714616537,
      "photo_count": 0,
      "listing_url": "https://www.centris.ca/fr/local-commercial~a-louer~longueuil-le-vieux-longueuil/12212839",
      "sqft": 2850,
      "description": "Magnifique espace de bureau de 2 850 pi2 rénové en 2020 et stratégiquement situé sur le Boulevard M...",
      "broker": "PMML Agence immobilière résidentielle et commerciale",
      "area": "boucherville",
      "area_label": "Boucherville",
      "transaction_type": "lease",
      "first_seen": "2026-06-06",
      "building_seen_before": true
    },
    {
      "mls_number": "9032394",
      "title": "Bâtisse commerciale à vendre à Longueuil (Saint-Hubert), Montérégie, 3541, Grande Allée, 9032394",
      "category": "Batisse Commerciale",
      "address": "Montérégie, 3541, Grande Allée",
      "city": "Montérégie",
      "price_value": "1100000",
      "price_display": "",
      "latitude": 45.49124302715063,
      "longitude": -73.47130676172674,
      "photo_count": 0,
      "listing_url": "https://www.centris.ca/fr/batisse-commerciale~a-vendre~longueuil-saint-hubert/9032394",
      "sqft": 2753,
      "description": "Immeuble commercial d'un étage de 2753 pi² sur un terrain de 5 774 pi². Actuellement, l'immeuble es...",
      "broker": "RE/MAX PRO-COMMERCIAL Agence immobilière",
      "area": "brossard",
      "area_label": "Brossard",
      "transaction_type": "sale",
      "first_seen": "2026-06-06",
      "building_seen_before": false
    },
    {
      "mls_number": "21603830",
      "title": "Local commercial à louer à Longueuil (Le Vieux-Longueuil), Montérégie, 50, Rue Saint-Charles Ouest, 21603830",
      "category": "Local Commercial",
      "address": "Montérégie, 50, Rue Saint-Charles Ouest",
      "city": "Montérégie",
      "price_value": "22",
      "price_display": "",
      "latitude": 45.53987834735641,
      "longitude": -73.50747760518321,
      "photo_count": 0,
      "listing_url": "https://www.centris.ca/fr/local-commercial~a-louer~longueuil-le-vieux-longueuil/21603830",
      "sqft": 6395,
      "description": "Suite 300 -- Dernier étage du 50 rue Saint-Charles Ouest à Longueuil. Plateau complet de ±6 395 pi²...",
      "broker": "KELLER WILLIAMS URBAIN Agence immobilière",
      "area": "longueuil",
      "area_label": "Longueuil",
      "transaction_type": "lease",
      "first_seen": "2026-06-06",
      "building_seen_before": false
    },
    {
      "mls_number": "26694540",
      "title": "Local commercial à louer à Longueuil (Le Vieux-Longueuil), Montérégie, 32, Rue Saint-Charles Ouest, local 390, 26694540",
      "category": "Local Commercial",
      "address": "Montérégie, 32, Rue Saint-Charles Ouest, local 390",
      "city": "Montérégie",
      "price_value": "1021",
      "price_display": "",
      "latitude": 45.53987834735641,
      "longitude": -73.50747760518321,
      "photo_count": 0,
      "listing_url": "https://www.centris.ca/fr/local-commercial~a-louer~longueuil-le-vieux-longueuil/26694540",
      "sqft": 400,
      "description": "Situé au 32, rue St-Charles Ouest à Longueuil, au coeur du Vieux-Longueuil, ce local de bureaux pre...",
      "broker": "RE/MAX EXTRA INC. Agence immobilière",
      "area": "longueuil",
      "area_label": "Longueuil",
      "transaction_type": "lease",
      "first_seen": "2026-06-06",
      "building_seen_before": true
    },
    {
      "mls_number": "18186987",
      "title": "Local commercial à louer à Saint-Bruno-de-Montarville, Montérégie, 1060, Rue Parent, local 100, 18186987",
      "category": "Local Commercial",
      "address": "Montérégie, 1060, Rue Parent, local 100",
      "city": "Montérégie",
      "price_value": "20",
      "price_display": "",
      "latitude": 45.529174651019275,
      "longitude": -73.36876003537327,
      "photo_count": 0,
      "listing_url": "https://www.centris.ca/fr/local-commercial~a-louer~saint-bruno-de-montarville/18186987",
      "sqft": 1258,
      "description": "Construction neuve (2020) - Facilement accessible par l'autoroute 30, à moins de 1 km à partir de l...",
      "broker": "INTERCOM SERVICES IMMOBILIERS Agence immobilière commerciale",
      "area": "st-hubert",
      "area_label": "Saint-Hubert",
      "transaction_type": "lease",
      "first_seen": "2026-06-06",
      "building_seen_before": true
    },
    {
      "mls_number": "15828927",
      "title": "Local commercial à louer à Châteauguay, Montérégie, 250, boulevard Ford, local H, 15828927",
      "category": "Local Commercial",
      "address": "Montérégie, 250, boulevard Ford, local H",
      "city": "Montérégie",
      "price_value": "3000",
      "price_display": "",
      "latitude": 45.34832511562854,
      "longitude": -73.70067556388676,
      "photo_count": 0,
      "listing_url": "https://www.centris.ca/fr/local-commercial~a-louer~chateauguay/15828927",
      "sqft": 3550,
      "description": "Splendide CONDO commercial et industriel situé dans le quartier industriel de Châteauguay à 5 minut...",
      "broker": "ROYAL LEPAGE VILLAGE Agence immobilière",
      "area": "chateauguay",
      "area_label": "Chateauguay",
      "transaction_type": "lease",
      "first_seen": "2026-06-06",
      "building_seen_before": false
    },
    {
      "mls_number": "18165975",
      "title": "Bâtisse commerciale à vendre à Châteauguay, Montérégie, 5555, Rue Non Disponible-Unavailable, 18165975",
      "category": "Batisse Commerciale",
      "address": "Montérégie, 5555, Rue Non Disponible-Unavailable",
      "city": "Montérégie",
      "price_value": "1315000",
      "price_display": "",
      "latitude": 45.365748521871865,
      "longitude": -73.7328539416194,
      "photo_count": 0,
      "listing_url": "https://www.centris.ca/fr/batisse-commerciale~a-vendre~chateauguay/18165975",
      "sqft": 1786,
      "description": "Opportunité unique!!Vous rêvez d'avoir votre entreprise avec une clientèle sans fin? Maison de retr...",
      "broker": "EXP AGENCE IMMOBILIÈRE Agence immobilière",
      "area": "chateauguay",
      "area_label": "Chateauguay",
      "transaction_type": "sale",
      "first_seen": "2026-06-06",
      "building_seen_before": false
    }
  ]
}