{
  "search_date": "2026-07-17T15:32:51.742372",
  "count": 14,
  "fresh_buildings": 8,
  "seen_buildings": 6,
  "listings": [
    {
      "mls_number": "12977819",
      "title": "Bâtisse commerciale à vendre à Varennes, Montérégie, 1645, boulevard Lionel-Boulet, 12977819",
      "category": "Batisse Commerciale",
      "address": "Montérégie, 1645, boulevard Lionel-Boulet",
      "city": "Montérégie",
      "price_value": "12000000",
      "price_display": "",
      "latitude": 45.62514899298549,
      "longitude": -73.38100503198802,
      "photo_count": 0,
      "listing_url": "https://www.centris.ca/fr/batisse-commerciale~a-vendre~varennes/12977819",
      "sqft": 1996,
      "description": "Immeuble commercial à couper le souffle situé dans le Novoparc de Varennes, offrant une excellente ...",
      "broker": "SERVICES IMMOBILIERS COMMERCIAUX AVISON YOUNG Agence immobilière",
      "area": "boucherville",
      "area_label": "Boucherville",
      "transaction_type": "lease",
      "first_seen": "2026-07-17",
      "building_seen_before": false
    },
    {
      "mls_number": "23768434",
      "title": "Local commercial à louer à Boucherville, Montérégie, 130, boulevard de Mortagne, local 200, 23768434",
      "category": "Local Commercial",
      "address": "Montérégie, 130, boulevard de Mortagne, local 200",
      "city": "Montérégie",
      "price_value": "28",
      "price_display": "",
      "latitude": 45.57507781893946,
      "longitude": -73.44894243171439,
      "photo_count": 0,
      "listing_url": "https://www.centris.ca/fr/local-commercial~a-louer~boucherville/23768434",
      "sqft": 5752,
      "description": "130, boulevard de Mortagne, 2e étage -- Boucherville (J4B 5M7) Superficie : 5 500 pi² | Disponibili...",
      "broker": "ROYAL LEPAGE TRADITION Agence immobilière",
      "area": "boucherville",
      "area_label": "Boucherville",
      "transaction_type": "lease",
      "first_seen": "2026-07-17",
      "building_seen_before": false
    },
    {
      "mls_number": "21664011",
      "title": "Local commercial à louer à Longueuil (Le Vieux-Longueuil), Montérégie, 2398, boulevard Marie-Victorin, local 202, 21664011",
      "category": "Local Commercial",
      "address": "Montérégie, 2398, boulevard Marie-Victorin, local 202",
      "city": "Montérégie",
      "price_value": "2576",
      "price_display": "",
      "latitude": 45.57753031142056,
      "longitude": -73.47642302513123,
      "photo_count": 0,
      "listing_url": "https://www.centris.ca/fr/local-commercial~a-louer~longueuil-le-vieux-longueuil/21664011",
      "sqft": 1061,
      "description": "Plusieurs  bureaux disponibles:  889 pi.ca. , 1 014  pi.ca. et  1 061 pi.ca.  Situé en façade de la...",
      "broker": "INTERCOM SERVICES IMMOBILIERS Agence immobilière commerciale",
      "area": "boucherville",
      "area_label": "Boucherville",
      "transaction_type": "lease",
      "first_seen": "2026-07-17",
      "building_seen_before": true
    },
    {
      "mls_number": "22379693",
      "title": "Local commercial à louer à Longueuil (Saint-Hubert), Montérégie, 5055, boulevard Cousineau, 22379693",
      "category": "Local Commercial",
      "address": "Montérégie, 5055, boulevard Cousineau",
      "city": "Montérégie",
      "price_value": "20",
      "price_display": "",
      "latitude": 45.50302998628467,
      "longitude": -73.425661213696,
      "photo_count": 0,
      "listing_url": "https://www.centris.ca/fr/local-commercial~a-louer~longueuil-saint-hubert/22379693",
      "sqft": 7228,
      "description": "MERCI DE VERIFIER, A titre de collaborateur, la rémunération est planifié à 12,000,00 plus   taxes,...",
      "broker": "TRUSTCAN AGENCE IMMOBILIÈRE Agence immobilière",
      "area": "brossard",
      "area_label": "Brossard",
      "transaction_type": "lease",
      "first_seen": "2026-07-17",
      "building_seen_before": false
    },
    {
      "mls_number": "21435926",
      "title": "Local commercial à louer à Brossard, Montérégie, 5773, boulevard Taschereau, local 104, 21435926",
      "category": "Local Commercial",
      "address": "Montérégie, 5773, boulevard Taschereau, local 104",
      "city": "Montérégie",
      "price_value": "30",
      "price_display": "",
      "latitude": 45.47899999190122,
      "longitude": -73.4652500320226,
      "photo_count": 0,
      "listing_url": "https://www.centris.ca/fr/local-commercial~a-louer~brossard/21435926",
      "sqft": null,
      "description": "Loyer de base : 30 $ le pied carré. Loyer additionnel pour l'année civile 2026 : 10 $ le pied carré...",
      "broker": "IMMOBILIER HIMALAYA REAL ESTATE CORP. Agence immobilière",
      "area": "brossard",
      "area_label": "Brossard",
      "transaction_type": "lease",
      "first_seen": "2026-07-17",
      "building_seen_before": false
    },
    {
      "mls_number": "12792180",
      "title": "Local commercial à louer à Longueuil (Le Vieux-Longueuil), Montérégie, 369, Rue Saint-Jean, local E, 12792180",
      "category": "Local Commercial",
      "address": "Montérégie, 369, Rue Saint-Jean, local E",
      "city": "Montérégie",
      "price_value": "1200",
      "price_display": "",
      "latitude": 45.536140971235,
      "longitude": -73.50578292505816,
      "photo_count": 0,
      "listing_url": "https://www.centris.ca/fr/local-commercial~a-louer~longueuil-le-vieux-longueuil/12792180",
      "sqft": 480,
      "description": "Au coeur du Vieux-Longueuil. Espace de 480 pi. ca. situé dans la section type marché public. Idéal ...",
      "broker": "ROYAL LEPAGE TRIOMPHE Agence immobilière",
      "area": "longueuil",
      "area_label": "Longueuil",
      "transaction_type": "lease",
      "first_seen": "2026-07-17",
      "building_seen_before": true
    },
    {
      "mls_number": "9052510",
      "title": "Local commercial à louer à Longueuil (Le Vieux-Longueuil), Montérégie, 386, Rue De Gentilly Ouest, local 107, 9052510",
      "category": "Local Commercial",
      "address": "Montérégie, 386, Rue De Gentilly Ouest, local 107",
      "city": "Montérégie",
      "price_value": "600",
      "price_display": "",
      "latitude": 45.531375710852444,
      "longitude": -73.4999958705157,
      "photo_count": 0,
      "listing_url": "https://www.centris.ca/fr/local-commercial~a-louer~longueuil-le-vieux-longueuil/9052510",
      "sqft": 100,
      "description": "Sur Centris.ca, découvrez la plus grande offre de propriété résidentielle à vendre.",
      "broker": "TRANSACTION IMMOBILIÈRE MULTI-SERVICES INCORPORÉE Agence immobilière",
      "area": "longueuil",
      "area_label": "Longueuil",
      "transaction_type": "lease",
      "first_seen": "2026-07-17",
      "building_seen_before": true
    },
    {
      "mls_number": "21261706",
      "title": "Local commercial à vendre à Longueuil (Le Vieux-Longueuil), Montérégie, 45, Place Charles-Le Moyne, local 95, 21261706",
      "category": "Local Commercial",
      "address": "Montérégie, 45, Place Charles-Le Moyne, local 95",
      "city": "Montérégie",
      "price_value": "597000",
      "price_display": "",
      "latitude": 45.52596931345761,
      "longitude": -73.52325500920415,
      "photo_count": 0,
      "listing_url": "https://www.centris.ca/fr/local-commercial~a-vendre~longueuil-le-vieux-longueuil/21261706",
      "sqft": 1991,
      "description": "Découvrez une rare opportunité d'acquérir des espaces de bureaux prestigieux dans un emplacement de...",
      "broker": "ROYAL LEPAGE DU QUARTIER H.Y. Agence immobilière",
      "area": "longueuil",
      "area_label": "Longueuil",
      "transaction_type": "sale",
      "first_seen": "2026-07-17",
      "building_seen_before": true
    },
    {
      "mls_number": "26980252",
      "title": "Commerce à vendre à Longueuil (Saint-Hubert), Montérégie, 1, Rue Non Disponible-Unavailable, 26980252",
      "category": "Commerce",
      "address": "Montérégie, 1, Rue Non Disponible-Unavailable",
      "city": "Montérégie",
      "price_value": "925000",
      "price_display": "",
      "latitude": 45.49747368134558,
      "longitude": -73.40561709925532,
      "photo_count": 0,
      "listing_url": "https://www.centris.ca/fr/commerce~a-vendre~longueuil-saint-hubert/26980252",
      "sqft": null,
      "description": "Sur Centris.ca, découvrez la plus grande offre de propriété résidentielle à vendre.",
      "broker": "GROUPE SUTTON EXCELLENCE INC. Agence immobilière",
      "area": "st-hubert",
      "area_label": "Saint-Hubert",
      "transaction_type": "sale",
      "first_seen": "2026-07-17",
      "building_seen_before": false
    },
    {
      "mls_number": "13663661",
      "title": "Commerce à vendre à Longueuil (Saint-Hubert), Montérégie, 6050, Chemin de la Savane, 13663661",
      "category": "Commerce",
      "address": "Montérégie, 6050, Chemin de la Savane",
      "city": "Montérégie",
      "price_value": "1100000",
      "price_display": "",
      "latitude": 45.52774922456592,
      "longitude": -73.41727229068056,
      "photo_count": 0,
      "listing_url": "https://www.centris.ca/fr/commerce~a-vendre~longueuil-saint-hubert/13663661",
      "sqft": null,
      "description": "Entreprise  fleurissante + immeuble commercial construction tout en béton est situé sur le chemin d...",
      "broker": "PGL AGENCE IMMOBILIÈRE Agence immobilière",
      "area": "st-hubert",
      "area_label": "Saint-Hubert",
      "transaction_type": "sale",
      "first_seen": "2026-07-17",
      "building_seen_before": true
    },
    {
      "mls_number": "25350380",
      "title": "Local commercial à louer à La Prairie, Montérégie, 1, Rue Non Disponible-Unavailable, 25350380",
      "category": "Local Commercial",
      "address": "Montérégie, 1, Rue Non Disponible-Unavailable",
      "city": "Montérégie",
      "price_value": "24",
      "price_display": "",
      "latitude": 45.408935621380806,
      "longitude": -73.49355706013739,
      "photo_count": 0,
      "listing_url": "https://www.centris.ca/fr/local-commercial~a-louer~la-prairie/25350380",
      "sqft": 2000,
      "description": "Excellent local commercial d'environ 1000 pi² à 2000 pi2 offrant une visibilité exceptionnelle, idé...",
      "broker": "CENTURY 21 AVENUE Agence immobilière",
      "area": "la-prairie",
      "area_label": "La Prairie",
      "transaction_type": "lease",
      "first_seen": "2026-07-17",
      "building_seen_before": false
    },
    {
      "mls_number": "11506205",
      "title": "Local commercial à louer à Châteauguay, Montérégie, 288, boulevard D'Anjou, local 120, 11506205",
      "category": "Local Commercial",
      "address": "Montérégie, 288, boulevard D'Anjou, local 120",
      "city": "Montérégie",
      "price_value": "25",
      "price_display": "",
      "latitude": 45.35848595201969,
      "longitude": -73.71896831318736,
      "photo_count": 0,
      "listing_url": "https://www.centris.ca/fr/local-commercial~a-louer~chateauguay/11506205",
      "sqft": 1809,
      "description": "Établissez votre clinique ou votre pratique professionnelle dans un prestigieux local de 1 809 pi2 ...",
      "broker": "PMML Agence immobilière résidentielle et commerciale",
      "area": "chateauguay",
      "area_label": "Chateauguay",
      "transaction_type": "lease",
      "first_seen": "2026-07-17",
      "building_seen_before": false
    },
    {
      "mls_number": "12756916",
      "title": "Local commercial à louer à Varennes, Montérégie, 2444, boulevard René-Gaultier, local 114, 12756916",
      "category": "Local Commercial",
      "address": "Montérégie, 2444, boulevard René-Gaultier, local 114",
      "city": "Montérégie",
      "price_value": "5500",
      "price_display": "",
      "latitude": 45.687405997887254,
      "longitude": -73.43039707280695,
      "photo_count": 0,
      "listing_url": "https://www.centris.ca/fr/local-commercial~a-louer~varennes/12756916",
      "sqft": 2800,
      "description": "Superbe local commercial idéalement situé au coeur de la ville de Varennes. Ce local de coin d'envi...",
      "broker": "GIOVANNI CAFARO Courtier immobilier commercial",
      "area": "varennes",
      "area_label": "Varennes",
      "transaction_type": "lease",
      "first_seen": "2026-07-17",
      "building_seen_before": true
    },
    {
      "mls_number": "20119311",
      "title": "Bâtisse commerciale à vendre à Charlemagne, Lanaudière, 216, Rue Notre-Dame, 20119311",
      "category": "Batisse Commerciale",
      "address": "Lanaudière, 216, Rue Notre-Dame",
      "city": "Lanaudière",
      "price_value": "999000",
      "price_display": "",
      "latitude": 45.720875602564774,
      "longitude": -73.48373607848771,
      "photo_count": 0,
      "listing_url": "https://www.centris.ca/fr/batisse-commerciale~a-vendre~charlemagne/20119311",
      "sqft": 8090,
      "description": "Localisation  idéale à Charlemagne près de Repentigny! Espace commercial offrant une excellente vis...",
      "broker": "RE/MAX ALLIANCE INC. Agence immobilière",
      "area": "varennes",
      "area_label": "Varennes",
      "transaction_type": "sale",
      "first_seen": "2026-07-17",
      "building_seen_before": false
    }
  ]
}